NL/deploy.py
NL/hello.py
NL/test.py
nlweb_org-0.1.63.dist-info/licenses/LICENSE
nlweb_org-0.1.63.dist-info/METADATA
nlweb_org-0.1.63.dist-info/WHEEL
nlweb_org-0.1.63.dist-info/top_level.txt
nlweb_org-0.1.63.dist-info/RECORD
