Metadata-Version: 2.4
Name: nlweb-org
Version: 0.1.63
Summary: Example package for nlweb.org domain-style imports
Author-email: Jorge Fonseca <jorge.m.j.fonseca@example.com>
License: MIT
Requires-Python: >=3.8
License-File: LICENSE
Requires-Dist: ruamel.yaml<0.18,>=0.16
Dynamic: license-file
